dodatni_primjeri/p6-primjer1/primjer1/scnt.vhd
library ieee;
use ieee.std_logic_1164.all;


entity scnt is
port(
	fclk:		in std_logic; 
	pin:		in std_logic; 
	bflag:		in std_logic; 
	eflag:		out std_logic;
	period:		out integer);  
end scnt;

architecture arch_scnt of scnt is

begin
process(fclk)

variable l_period: integer := 0;
variable state: integer := 0;

begin
	if fclk'event and fclk='1' then
		
		if state = 0 then
			if bflag = '1' then						-- initiate the measurement algo
				state := state + 1;
				l_period := 0;
				period <= 0;
				report "begin measurement";
			end if;
		elsif state = 1 then
			
			if pin = '1' then
				l_period := l_period + 1;
				
			else									-- measurement completed
				period <= l_period;
				eflag <= '1';
				state := state + 1;
				
				--report "measurement completed: " &integer'image(l_period);
			end if;	
		elsif state = 2 then
			if pin = '1' then
				eflag <= '0';
				l_period := 1;
				state := 1;
			end if;	
		end if;
		
		if bflag = '0' then
				report "period 0";
			period <= 0;
			state := 0;
		end if;
	end if;
end process ;
end arch_scnt;

dodatni_primjeri/p6-primjer1/primjer1/pwm.vhd
library ieee;
use ieee.std_logic_1164.all;


entity pwm is
port(
	fclk:		in std_logic; 
	duty:		in integer; 
	period:		in integer;
	pin:		out std_logic);  
end pwm;

architecture arch_pwm of pwm is
signal tmp: std_logic := '0';

begin
process(fclk)

variable cnt: integer:=0;
begin
    if fclk'event and fclk='1' then
		if cnt < duty then
			pin <= '1';
		elsif cnt < period then
			pin <= '0';
		else
			cnt:=0;
			pin <= '1';
		end if;
		cnt := cnt + 1;
   end if;
end process ;
end arch_pwm;

dodatni_primjeri/p6-primjer1/primjer1/top_tb.vhd
library ieee;
use ieee.std_logic_1164.all;

entity top_tb is
end top_tb;

architecture arctop_tb of top_tb is

component pwm 
port(
	fclk:		in std_logic; 
	duty:		in integer; 
	period:		in integer;
	pin:		out std_logic); 
end component;

component scnt 
port(
	fclk:		in std_logic; 
	pin:		in std_logic; 
	bflag:		in std_logic; 
	eflag:		out std_logic;
	period:		out integer); 
end component;


signal endsim_main: std_logic:='0';
signal endsim_clk: std_logic:='0';
signal endsim: std_logic:='0';

signal fclk: std_logic:='0';
signal led: std_logic:='0';
signal duty: integer := 50;
signal period: integer := 100;		-- signal with target period

signal bflag: std_logic:='0';
signal eflag: std_logic:='0';
signal mperiod: integer := 0;		-- signal holding result of measurement


begin
	c_pwm: pwm port map (fclk=>fclk, pin=>led , duty=>duty, period=>period);	
	c_scnt: scnt port map (fclk=>fclk, pin=>led , bflag=>bflag, eflag=>eflag, period=>mperiod);	
	endsim <= endsim_main or endsim_clk;

main: process
	variable state: integer:= 0;
	variable l_duty: integer:= 10;
	begin
		
		report "start simulation";
		duty <= 10;
		period <= 100;
		
		wait for 1000 ns;
		endsim_main <= '1';
		
		report "test completed";
		wait;
		
		--if state = 0 then
			--report "start simulation";
			---- set target parameters for the source
			--duty <= 10;
			--period <= 100;
			--state := state + 1;
			--bflag <= '1';
		--elsif state = 1 then
			--if eflag = '1' then
				--state := state + 1;
			--end if;
		--elsif state = 2 then
			--if eflag = '0' then
				--l_duty := l_duty*2;
				--if(l_duty >= 100) then
					--report "test completed";
					--endsim_main <= '1';
					--wait;
				--else
					--report "measurement done: " &integer'image(mperiod);
					--duty <= l_duty;
					--state := 1;
				--end if;
			--end if;
		--end if;
		
		wait for 1 ns;
	end process;	


	
-- clk generation process for 500 MHz clock
clk:	process
		variable fclk_end: integer:= 50000; 		-- number of FPGA clock cycles
		variable fclk_cnt: integer:=0;
		
		begin
			fclk <= '1';
			wait for 1 ns;
			fclk <= '0';
			wait for 1 ns;
			
			
			fclk_cnt := fclk_cnt + 1;
			-- stop clk generation if the simulation process hangs
			if(fclk_cnt = fclk_end) then
				report "fpga clock exhausted";
				endsim_clk <= '1';
				wait;
			end if;
			
			-- stop the clock generation if simulation process completed
			if(endsim = '1') then
				report "fpga clock shutdown";
				wait;
			end if;
				
		end process;	
end arctop_tb;

dodatni_primjeri/p6-primjer1/primjer1/top.vcd
$date
  Tue May  2 23:05:48 2023
$end
$version
  GHDL v0
$end
$timescale
  1 fs
$end
$scope module standard $end
$upscope $end
$scope module std_logic_1164 $end
$upscope $end
$scope module top_tb $end
$var reg 1 ! endsim_main $end
$var reg 1 " endsim_clk $end
$var reg 1 # endsim $end
$var reg 1 $ fclk $end
$var reg 1 % led $end
$var integer 32 & duty $end
$var integer 32 ' period $end
$var reg 1 ( bflag $end
$var reg 1 ) eflag $end
$var integer 32 * mperiod $end
$scope module c_pwm $end
$var reg 1 + fclk $end
$var integer 32 , duty $end
$var integer 32 - period $end
$var reg 1 . pin $end
$var reg 1 / tmp $end
$upscope $end
$scope module c_scnt $end
$var reg 1 0 fclk $end
$var reg 1 1 pin $end
$var reg 1 2 bflag $end
$var reg 1 3 eflag $end
$var integer 32 4 period $end
$upscope $end
$upscope $end
$enddefinitions $end
#0
0!
0"
0#
1$
1%
b1010 &
b1100100 '
0(
U)
b0 *
1+
b1010 ,
b1100100 -
1.
0/
10
11
02
U3
b0 4
#1000000
0$
0+
00
#2000000
1$
1+
10
#3000000
0$
0+
00
#4000000
1$
1+
10
#5000000
0$
0+
00
#6000000
1$
1+
10
#7000000
0$
0+
00
#8000000
1$
1+
10
#9000000
0$
0+
00
#10000000
1$
1+
10
#11000000
0$
0+
00
#12000000
1$
1+
10
#13000000
0$
0+
00
#14000000
1$
1+
10
#15000000
0$
0+
00
#16000000
1$
1+
10
#17000000
0$
0+
00
#18000000
1$
1+
10
#19000000
0$
0+
00
#20000000
1$
0%
1+
0.
10
01
#21000000
0$
0+
00
#22000000
1$
1+
10
#23000000
0$
0+
00
#24000000
1$
1+
10
#25000000
0$
0+
00
#26000000
1$
1+
10
#27000000
0$
0+
00
#28000000
1$
1+
10
#29000000
0$
0+
00
#30000000
1$
1+
10
#31000000
0$
0+
00
#32000000
1$
1+
10
#33000000
0$
0+
00
#34000000
1$
1+
10
#35000000
0$
0+
00
#36000000
1$
1+
10
#37000000
0$
0+
00
#38000000
1$
1+
10
#39000000
0$
0+
00
#40000000
1$
1+
10
#41000000
0$
0+
00
#42000000
1$
1+
10
#43000000
0$
0+
00
#44000000
1$
1+
10
#45000000
0$
0+
00
#46000000
1$
1+
10
#47000000
0$
0+
00
#48000000
1$
1+
10
#49000000
0$
0+
00
#50000000
1$
1+
10
#51000000
0$
0+
00
#52000000
1$
1+
10
#53000000
0$
0+
00
#54000000
1$
1+
10
#55000000
0$
0+
00
#56000000
1$
1+
10
#57000000
0$
0+
00
#58000000
1$
1+
10
#59000000
0$
0+
00
#60000000
1$
1+
10
#61000000
0$
0+
00
#62000000
1$
1+
10
#63000000
0$
0+
00
#64000000
1$
1+
10
#65000000
0$
0+
00
#66000000
1$
1+
10
#67000000
0$
0+
00
#68000000
1$
1+
10
#69000000
0$
0+
00
#70000000
1$
1+
10
#71000000
0$
0+
00
#72000000
1$
1+
10
#73000000
0$
0+
00
#74000000
1$
1+
10
#75000000
0$
0+
00
#76000000
1$
1+
10
#77000000
0$
0+
00
#78000000
1$
1+
10
#79000000
0$
0+
00
#80000000
1$
1+
10
#81000000
0$
0+
00
#82000000
1$
1+
10
#83000000
0$
0+
00
#84000000
1$
1+
10
#85000000
0$
0+
00
#86000000
1$
1+
10
#87000000
0$
0+
00
#88000000
1$
1+
10
#89000000
0$
0+
00
#90000000
1$
1+
10
#91000000
0$
0+
00
#92000000
1$
1+
10
#93000000
0$
0+
00
#94000000
1$
1+
10
#95000000
0$
0+
00
#96000000
1$
1+
10
#97000000
0$
0+
00
#98000000
1$
1+
10
#99000000
0$
0+
00
#100000000
1$
1+
10
#101000000
0$
0+
00
#102000000
1$
1+
10
#103000000
0$
0+
00
#104000000
1$
1+
10
#105000000
0$
0+
00
#106000000
1$
1+
10
#107000000
0$
0+
00
#108000000
1$
1+
10
#109000000
0$
0+
00
#110000000
1$
1+
10
#111000000
0$
0+
00
#112000000
1$
1+
10
#113000000
0$
0+
00
#114000000
1$
1+
10
#115000000
0$
0+
00
#116000000
1$
1+
10
#117000000
0$
0+
00
#118000000
1$
1+
10
#119000000
0$
0+
00
#120000000
1$
1+
10
#121000000
0$
0+
00
#122000000
1$
1+
10
#123000000
0$
0+
00
#124000000
1$
1+
10
#125000000
0$
0+
00
#126000000
1$
1+
10
#127000000
0$
0+
00
#128000000
1$
1+
10
#129000000
0$
0+
00
#130000000
1$
1+
10
#131000000
0$
0+
00
#132000000
1$
1+
10
#133000000
0$
0+
00
#134000000
1$
1+
10
#135000000
0$
0+
00
#136000000
1$
1+
10
#137000000
0$
0+
00
#138000000
1$
1+
10
#139000000
0$
0+
00
#140000000
1$
1+
10
#141000000
0$
0+
00
#142000000
1$
1+
10
#143000000
0$
0+
00
#144000000
1$
1+
10
#145000000
0$
0+
00
#146000000
1$
1+
10
#147000000
0$
0+
00
#148000000
1$
1+
10
#149000000
0$
0+
00
#150000000
1$
1+
10
#151000000
0$
0+
00
#152000000
1$
1+
10
#153000000
0$
0+
00
#154000000
1$
1+
10
#155000000
0$
0+
00
#156000000
1$
1+
10
#157000000
0$
0+
00
#158000000
1$
1+
10
#159000000
0$
0+
00
#160000000
1$
1+
10
#161000000
0$
0+
00
#162000000
1$
1+
10
#163000000
0$
0+
00
#164000000
1$
1+
10
#165000000
0$
0+
00
#166000000
1$
1+
10
#167000000
0$
0+
00
#168000000
1$
1+
10
#169000000
0$
0+
00
#170000000
1$
1+
10
#171000000
0$
0+
00
#172000000
1$
1+
10
#173000000
0$
0+
00
#174000000
1$
1+
10
#175000000
0$
0+
00
#176000000
1$
1+
10
#177000000
0$
0+
00
#178000000
1$
1+
10
#179000000
0$
0+
00
#180000000
1$
1+
10
#181000000
0$
0+
00
#182000000
1$
1+
10
#183000000
0$
0+
00
#184000000
1$
1+
10
#185000000
0$
0+
00
#186000000
1$
1+
10
#187000000
0$
0+
00
#188000000
1$
1+
10
#189000000
0$
0+
00
#190000000
1$
1+
10
#191000000
0$
0+
00
#192000000
1$
1+
10
#193000000
0$
0+
00
#194000000
1$
1+
10
#195000000
0$
0+
00
#196000000
1$
1+
10
#197000000
0$
0+
00
#198000000
1$
1+
10
#199000000
0$
0+
00
#200000000
1$
1%
1+
1.
10
11
#201000000
0$
0+
00
#202000000
1$
1+
10
#203000000
0$
0+
00
#204000000
1$
1+
10
#205000000
0$
0+
00
#206000000
1$
1+
10
#207000000
0$
0+
00
#208000000
1$
1+
10
#209000000
0$
0+
00
#210000000
1$
1+
10
#211000000
0$
0+
00
#212000000
1$
1+
10
#213000000
0$
0+
00
#214000000
1$
1+
10
#215000000
0$
0+
00
#216000000
1$
1+
10
#217000000
0$
0+
00
#218000000
1$
1+
10
#219000000
0$
0+
00
#220000000
1$
0%
1+
0.
10
01
#221000000
0$
0+
00
#222000000
1$
1+
10
#223000000
0$
0+
00
#224000000
1$
1+
10
#225000000
0$
0+
00
#226000000
1$
1+
10
#227000000
0$
0+
00
#228000000
1$
1+
10
#229000000
0$
0+
00
#230000000
1$
1+
10
#231000000
0$
0+
00
#232000000
1$
1+
10
#233000000
0$
0+
00
#234000000
1$
1+
10
#235000000
0$
0+
00
#236000000
1$
1+
10
#237000000
0$
0+
00
#238000000
1$
1+
10
#239000000
0$
0+
00
#240000000
1$
1+
10
#241000000
0$
0+
00
#242000000
1$
1+
10
#243000000
0$
0+
00
#244000000
1$
1+
10
#245000000
0$
0+
00
#246000000
1$
1+
10
#247000000
0$
0+
00
#248000000
1$
1+
10
#249000000
0$
0+
00
#250000000
1$
1+
10
#251000000
0$
0+
00
#252000000
1$
1+
10
#253000000
0$
0+
00
#254000000
1$
1+
10
#255000000
0$
0+
00
#256000000
1$
1+
10
#257000000
0$
0+
00
#258000000
1$
1+
10
#259000000
0$
0+
00
#260000000
1$
1+
10
#261000000
0$
0+
00
#262000000
1$
1+
10
#263000000
0$
0+
00
#264000000
1$
1+
10
#265000000
0$
0+
00
#266000000
1$
1+
10
#267000000
0$
0+
00
#268000000
1$
1+
10
#269000000
0$
0+
00
#270000000
1$
1+
10
#271000000
0$
0+
00
#272000000
1$
1+
10
#273000000
0$
0+
00
#274000000
1$
1+
10
#275000000
0$
0+
00
#276000000
1$
1+
10
#277000000
0$
0+
00
#278000000
1$
1+
10
#279000000
0$
0+
00
#280000000
1$
1+
10
#281000000
0$
0+
00
#282000000
1$
1+
10
#283000000
0$
0+
00
#284000000
1$
1+
10
#285000000
0$
0+
00
#286000000
1$
1+
10
#287000000
0$
0+
00
#288000000
1$
1+
10
#289000000
0$
0+
00
#290000000
1$
1+
10
#291000000
0$
0+
00
#292000000
1$
1+
10
#293000000
0$
0+
00
#294000000
1$
1+
10
#295000000
0$
0+
00
#296000000
1$
1+
10
#297000000
0$
0+
00
#298000000
1$
1+
10
#299000000
0$
0+
00
#300000000
1$
1+
10
#301000000
0$
0+
00
#302000000
1$
1+
10
#303000000
0$
0+
00
#304000000
1$
1+
10
#305000000
0$
0+
00
#306000000
1$
1+
10
#307000000
0$
0+
00
#308000000
1$
1+
10
#309000000
0$
0+
00
#310000000
1$
1+
10
#311000000
0$
0+
00
#312000000
1$
1+
10
#313000000
0$
0+
00
#314000000
1$
1+
10
#315000000
0$
0+
00
#316000000
1$
1+
10
#317000000
0$
0+
00
#318000000
1$
1+
10
#319000000
0$
0+
00
#320000000
1$
1+
10
#321000000
0$
0+
00
#322000000
1$
1+
10
#323000000
0$
0+
00
#324000000
1$
1+
10
#325000000
0$
0+
00
#326000000
1$
1+
10
#327000000
0$
0+
00
#328000000
1$
1+
10
#329000000
0$
0+
00
#330000000
1$
1+
10
#331000000
0$
0+
00
#332000000
1$
1+
10
#333000000
0$
0+
00
#334000000
1$
1+
10
#335000000
0$
0+
00
#336000000
1$
1+
10
#337000000
0$
0+
00
#338000000
1$
1+
10
#339000000
0$
0+
00
#340000000
1$
1+
10
#341000000
0$
0+
00
#342000000
1$
1+
10
#343000000
0$
0+
00
#344000000
1$
1+
10
#345000000
0$
0+
00
#346000000
1$
1+
10
#347000000
0$
0+
00
#348000000
1$
1+
10
#349000000
0$
0+
00
#350000000
1$
1+
10
#351000000
0$
0+
00
#352000000
1$
1+
10
#353000000
0$
0+
00
#354000000
1$
1+
10
#355000000
0$
0+
00
#356000000
1$
1+
10
#357000000
0$
0+
00
#358000000
1$
1+
10
#359000000
0$
0+
00
#360000000
1$
1+
10
#361000000
0$
0+
00
#362000000
1$
1+
10
#363000000
0$
0+
00
#364000000
1$
1+
10
#365000000
0$
0+
00
#366000000
1$
1+
10
#367000000
0$
0+
00
#368000000
1$
1+
10
#369000000
0$
0+
00
#370000000
1$
1+
10
#371000000
0$
0+
00
#372000000
1$
1+
10
#373000000
0$
0+
00
#374000000
1$
1+
10
#375000000
0$
0+
00
#376000000
1$
1+
10
#377000000
0$
0+
00
#378000000
1$
1+
10
#379000000
0$
0+
00
#380000000
1$
1+
10
#381000000
0$
0+
00
#382000000
1$
1+
10
#383000000
0$
0+
00
#384000000
1$
1+
10
#385000000
0$
0+
00
#386000000
1$
1+
10
#387000000
0$
0+
00
#388000000
1$
1+
10
#389000000
0$
0+
00
#390000000
1$
1+
10
#391000000
0$
0+
00
#392000000
1$
1+
10
#393000000
0$
0+
00
#394000000
1$
1+
10
#395000000
0$
0+
00
#396000000
1$
1+
10
#397000000
0$
0+
00
#398000000
1$
1+
10
#399000000
0$
0+
00
#400000000
1$
1%
1+
1.
10
11
#401000000
0$
0+
00
#402000000
1$
1+
10
#403000000
0$
0+
00
#404000000
1$
1+
10
#405000000
0$
0+
00
#406000000
1$
1+
10
#407000000
0$
0+
00
#408000000
1$
1+
10
#409000000
0$
0+
00
#410000000
1$
1+
10
#411000000
0$
0+
00
#412000000
1$
1+
10
#413000000
0$
0+
00
#414000000
1$
1+
10
#415000000
0$
0+
00
#416000000
1$
1+
10
#417000000
0$
0+
00
#418000000
1$
1+
10
#419000000
0$
0+
00
#420000000
1$
0%
1+
0.
10
01
#421000000
0$
0+
00
#422000000
1$
1+
10
#423000000
0$
0+
00
#424000000
1$
1+
10
#425000000
0$
0+
00
#426000000
1$
1+
10
#427000000
0$
0+
00
#428000000
1$
1+
10
#429000000
0$
0+
00
#430000000
1$
1+
10
#431000000
0$
0+
00
#432000000
1$
1+
10
#433000000
0$
0+
00
#434000000
1$
1+
10
#435000000
0$
0+
00
#436000000
1$
1+
10
#437000000
0$
0+
00
#438000000
1$
1+
10
#439000000
0$
0+
00
#440000000
1$
1+
10
#441000000
0$
0+
00
#442000000
1$
1+
10
#443000000
0$
0+
00
#444000000
1$
1+
10
#445000000
0$
0+
00
#446000000
1$
1+
10
#447000000
0$
0+
00
#448000000
1$
1+
10
#449000000
0$
0+
00
#450000000
1$
1+
10
#451000000
0$
0+
00
#452000000
1$
1+
10
#453000000
0$
0+
00
#454000000
1$
1+
10
#455000000
0$
0+
00
#456000000
1$
1+
10
#457000000
0$
0+
00
#458000000
1$
1+
10
#459000000
0$
0+
00
#460000000
1$
1+
10
#461000000
0$
0+
00
#462000000
1$
1+
10
#463000000
0$
0+
00
#464000000
1$
1+
10
#465000000
0$
0+
00
#466000000
1$
1+
10
#467000000
0$
0+
00
#468000000
1$
1+
10
#469000000
0$
0+
00
#470000000
1$
1+
10
#471000000
0$
0+
00
#472000000
1$
1+
10
#473000000
0$
0+
00
#474000000
1$
1+
10
#475000000
0$
0+
00
#476000000
1$
1+
10
#477000000
0$
0+
00
#478000000
1$
1+
10
#479000000
0$
0+
00
#480000000
1$
1+
10
#481000000
0$
0+
00
#482000000
1$
1+
10
#483000000
0$
0+
00
#484000000
1$
1+
10
#485000000
0$
0+
00
#486000000
1$
1+
10
#487000000
0$
0+
00
#488000000
1$
1+
10
#489000000
0$
0+
00
#490000000
1$
1+
10
#491000000
0$
0+
00
#492000000
1$
1+
10
#493000000
0$
0+
00
#494000000
1$
1+
10
#495000000
0$
0+
00
#496000000
1$
1+
10
#497000000
0$
0+
00
#498000000
1$
1+
10
#499000000
0$
0+
00
#500000000
1$
1+
10
#501000000
0$
0+
00
#502000000
1$
1+
10
#503000000
0$
0+
00
#504000000
1$
1+
10
#505000000
0$
0+
00
#506000000
1$
1+
10
#507000000
0$
0+
00
#508000000
1$
1+
10
#509000000
0$
0+
00
#510000000
1$
1+
10
#511000000
0$
0+
00
#512000000
1$
1+
10
#513000000
0$
0+
00
#514000000
1$
1+
10
#515000000
0$
0+
00
#516000000
1$
1+
10
#517000000
0$
0+
00
#518000000
1$
1+
10
#519000000
0$
0+
00
#520000000
1$
1+
10
#521000000
0$
0+
00
#522000000
1$
1+
10
#523000000
0$
0+
00
#524000000
1$
1+
10
#525000000
0$
0+
00
#526000000
1$
1+
10
#527000000
0$
0+
00
#528000000
1$
1+
10
#529000000
0$
0+
00
#530000000
1$
1+
10
#531000000
0$
0+
00
#532000000
1$
1+
10
#533000000
0$
0+
00
#534000000
1$
1+
10
#535000000
0$
0+
00
#536000000
1$
1+
10
#537000000
0$
0+
00
#538000000
1$
1+
10
#539000000
0$
0+
00
#540000000
1$
1+
10
#541000000
0$
0+
00
#542000000
1$
1+
10
#543000000
0$
0+
00
#544000000
1$
1+
10
#545000000
0$
0+
00
#546000000
1$
1+
10
#547000000
0$
0+
00
#548000000
1$
1+
10
#549000000
0$
0+
00
#550000000
1$
1+
10
#551000000
0$
0+
00
#552000000
1$
1+
10
#553000000
0$
0+
00
#554000000
1$
1+
10
#555000000
0$
0+
00
#556000000
1$
1+
10
#557000000
0$
0+
00
#558000000
1$
1+
10
#559000000
0$
0+
00
#560000000
1$
1+
10
#561000000
0$
0+
00
#562000000
1$
1+
10
#563000000
0$
0+
00
#564000000
1$
1+
10
#565000000
0$
0+
00
#566000000
1$
1+
10
#567000000
0$
0+
00
#568000000
1$
1+
10
#569000000
0$
0+
00
#570000000
1$
1+
10
#571000000
0$
0+
00
#572000000
1$
1+
10
#573000000
0$
0+
00
#574000000
1$
1+
10
#575000000
0$
0+
00
#576000000
1$
1+
10
#577000000
0$
0+
00
#578000000
1$
1+
10
#579000000
0$
0+
00
#580000000
1$
1+
10
#581000000
0$
0+
00
#582000000
1$
1+
10
#583000000
0$
0+
00
#584000000
1$
1+
10
#585000000
0$
0+
00
#586000000
1$
1+
10
#587000000
0$
0+
00
#588000000
1$
1+
10
#589000000
0$
0+
00
#590000000
1$
1+
10
#591000000
0$
0+
00
#592000000
1$
1+
10
#593000000
0$
0+
00
#594000000
1$
1+
10
#595000000
0$
0+
00
#596000000
1$
1+
10
#597000000
0$
0+
00
#598000000
1$
1+
10
#599000000
0$
0+
00
#600000000
1$
1%
1+
1.
10
11
#601000000
0$
0+
00
#602000000
1$
1+
10
#603000000
0$
0+
00
#604000000
1$
1+
10
#605000000
0$
0+
00
#606000000
1$
1+
10
#607000000
0$
0+
00
#608000000
1$
1+
10
#609000000
0$
0+
00
#610000000
1$
1+
10
#611000000
0$
0+
00
#612000000
1$
1+
10
#613000000
0$
0+
00
#614000000
1$
1+
10
#615000000
0$
0+
00
#616000000
1$
1+
10
#617000000
0$
0+
00
#618000000
1$
1+
10
#619000000
0$
0+
00
#620000000
1$
0%
1+
0.
10
01
