dodatni_primjeri/p5-primjer12/primjer12/top.vhd
library ieee;
use ieee.std_logic_1164.all;


entity top is
port(
	fclk:		in std_logic; 
	led:		out std_logic);  
end top;

architecture arch_top of top is
signal tmp: std_logic := '0';

begin
process(fclk)

variable cnt: integer:=0;
variable duty: integer:=1;
variable dutycnt: integer:=0;
variable flag: integer := 0;
begin
    if fclk'event and fclk='1' then
		if cnt = 0 then
			tmp <= '1';
		else
			tmp <= '0';
		end if;
			
		if cnt<duty then
			cnt:=cnt+1;
			led<='1';
			
		elsif cnt<100 then
			cnt:=cnt+1;
			led<='0';
			
			
		else
			cnt:=0;
			led<='0';
			dutycnt := dutycnt + 1;
			
			if(dutycnt >= 1) then
				
				dutycnt := 0;
				duty := duty*2;
				
				if(duty >= 100) then
					duty := 1;
				end if;
			end if;
			
		end if;
  
   end if;
end process ;
end arch_top;

dodatni_primjeri/p5-primjer12/primjer12/top_tb.vhd
library ieee;
use ieee.std_logic_1164.all;

entity top_tb is
end top_tb;

architecture arctop_tb of top_tb is

component top 
port(
	fclk:		in std_logic; 
    led:	out std_logic);  
end component;


signal fclk: std_logic:='0';
signal led: std_logic:='0';
signal endsim_main: std_logic:='0';
signal endsim_clk: std_logic:='0';
signal endsim: std_logic:='0';


begin
	mycomp: top port map (fclk=>fclk, led=>led);	
	endsim <= endsim_main or endsim_clk;

main: process
	
	begin
		report "start simulation";
		
		wait for 4000 ns;
		endsim_main <= '1';
			
		report "test completed";
		wait;
		
	end process;	


	
-- clk generation process for 500 MHz clock
clk:	process
		variable fclk_end: integer:= 5000; 		-- number of FPGA clock cycles
		variable fclk_cnt: integer:=0;
		
		begin
			fclk <= '1';
			wait for 1 ns;
			fclk <= '0';
			wait for 1 ns;
			
			
			fclk_cnt := fclk_cnt + 1;
			-- stop clk generation if the simulation process hangs
			if(fclk_cnt = fclk_end) then
				report "fpga clock exhausted";
				endsim_clk <= '1';
				wait;
			end if;
			
			-- stop the clock generation if simulation process completed
			if(endsim = '1') then
				report "fpga clock shutdown";
				wait;
			end if;
				
		end process;	
end arctop_tb;

dodatni_primjeri/p5-primjer12/primjer12/top.vcd
$date
  Tue May  2 21:47:15 2023
$end
$version
  GHDL v0
$end
$timescale
  1 fs
$end
$scope module standard $end
$upscope $end
$scope module std_logic_1164 $end
$upscope $end
$scope module top_tb $end
$var reg 1 ! fclk $end
$var reg 1 " led $end
$var reg 1 # endsim_main $end
$var reg 1 $ endsim_clk $end
$var reg 1 % endsim $end
$scope module mycomp $end
$var reg 1 & fclk $end
$var reg 1 ' led $end
$var reg 1 ( tmp $end
$upscope $end
$upscope $end
$enddefinitions $end
#0
1!
1"
0#
0$
0%
1&
1'
1(
#1000000
0!
0&
#2000000
1!
0"
1&
0'
0(
#3000000
0!
0&
#4000000
1!
1&
#5000000
0!
0&
#6000000
1!
1&
#7000000
0!
0&
#8000000
1!
1&
#9000000
0!
0&
#10000000
1!
1&
#11000000
0!
0&
#12000000
1!
1&
#13000000
0!
0&
#14000000
1!
1&
#15000000
0!
0&
#16000000
1!
1&
#17000000
0!
0&
#18000000
1!
1&
#19000000
0!
0&
#20000000
1!
1&
#21000000
0!
0&
#22000000
1!
1&
#23000000
0!
0&
#24000000
1!
1&
#25000000
0!
0&
#26000000
1!
1&
#27000000
0!
0&
#28000000
1!
1&
#29000000
0!
0&
#30000000
1!
1&
#31000000
0!
0&
#32000000
1!
1&
#33000000
0!
0&
#34000000
1!
1&
#35000000
0!
0&
#36000000
1!
1&
#37000000
0!
0&
#38000000
1!
1&
#39000000
0!
0&
#40000000
1!
1&
#41000000
0!
0&
#42000000
1!
1&
#43000000
0!
0&
#44000000
1!
1&
#45000000
0!
0&
#46000000
1!
1&
#47000000
0!
0&
#48000000
1!
1&
#49000000
0!
0&
#50000000
1!
1&
#51000000
0!
0&
#52000000
1!
1&
#53000000
0!
0&
#54000000
1!
1&
#55000000
0!
0&
#56000000
1!
1&
#57000000
0!
0&
#58000000
1!
1&
#59000000
0!
0&
#60000000
1!
1&
#61000000
0!
0&
#62000000
1!
1&
#63000000
0!
0&
#64000000
1!
1&
#65000000
0!
0&
#66000000
1!
1&
#67000000
0!
0&
#68000000
1!
1&
#69000000
0!
0&
#70000000
1!
1&
#71000000
0!
0&
#72000000
1!
1&
#73000000
0!
0&
#74000000
1!
1&
#75000000
0!
0&
#76000000
1!
1&
#77000000
0!
0&
#78000000
1!
1&
#79000000
0!
0&
#80000000
1!
1&
#81000000
0!
0&
#82000000
1!
1&
#83000000
0!
0&
#84000000
1!
1&
#85000000
0!
0&
#86000000
1!
1&
#87000000
0!
0&
#88000000
1!
1&
#89000000
0!
0&
#90000000
1!
1&
#91000000
0!
0&
#92000000
1!
1&
#93000000
0!
0&
#94000000
1!
1&
#95000000
0!
0&
#96000000
1!
1&
#97000000
0!
0&
#98000000
1!
1&
#99000000
0!
0&
#100000000
1!
1&
#101000000
0!
0&
#102000000
1!
1&
#103000000
0!
0&
#104000000
1!
1&
#105000000
0!
0&
#106000000
1!
1&
#107000000
0!
0&
#108000000
1!
1&
#109000000
0!
0&
#110000000
1!
1&
#111000000
0!
0&
#112000000
1!
1&
#113000000
0!
0&
#114000000
1!
1&
#115000000
0!
0&
#116000000
1!
1&
#117000000
0!
0&
#118000000
1!
1&
#119000000
0!
0&
#120000000
1!
1&
#121000000
0!
0&
#122000000
1!
1&
#123000000
0!
0&
#124000000
1!
1&
#125000000
0!
0&
#126000000
1!
1&
#127000000
0!
0&
#128000000
1!
1&
#129000000
0!
0&
#130000000
1!
1&
#131000000
0!
0&
#132000000
1!
1&
#133000000
0!
0&
#134000000
1!
1&
#135000000
0!
0&
#136000000
1!
1&
#137000000
0!
0&
#138000000
1!
1&
#139000000
0!
0&
#140000000
1!
1&
#141000000
0!
0&
#142000000
1!
1&
#143000000
0!
0&
#144000000
1!
1&
#145000000
0!
0&
#146000000
1!
1&
#147000000
0!
0&
#148000000
1!
1&
#149000000
0!
0&
#150000000
1!
1&
#151000000
0!
0&
#152000000
1!
1&
#153000000
0!
0&
#154000000
1!
1&
#155000000
0!
0&
#156000000
1!
1&
#157000000
0!
0&
#158000000
1!
1&
#159000000
0!
0&
#160000000
1!
1&
#161000000
0!
0&
#162000000
1!
1&
#163000000
0!
0&
#164000000
1!
1&
#165000000
0!
0&
#166000000
1!
1&
#167000000
0!
0&
#168000000
1!
1&
#169000000
0!
0&
#170000000
1!
1&
#171000000
0!
0&
#172000000
1!
1&
#173000000
0!
0&
#174000000
1!
1&
#175000000
0!
0&
#176000000
1!
1&
#177000000
0!
0&
#178000000
1!
1&
#179000000
0!
0&
#180000000
1!
1&
#181000000
0!
0&
#182000000
1!
1&
#183000000
0!
0&
#184000000
1!
1&
#185000000
0!
0&
#186000000
1!
1&
#187000000
0!
0&
#188000000
1!
1&
#189000000
0!
0&
#190000000
1!
1&
#191000000
0!
0&
#192000000
1!
1&
#193000000
0!
0&
#194000000
1!
1&
#195000000
0!
0&
#196000000
1!
1&
#197000000
0!
0&
#198000000
1!
1&
#199000000
0!
0&
#200000000
1!
1&
#201000000
0!
0&
#202000000
1!
1"
1&
1'
1(
#203000000
0!
0&
#204000000
1!
1&
0(
#205000000
0!
0&
#206000000
1!
0"
1&
0'
#207000000
0!
0&
#208000000
1!
1&
#209000000
0!
0&
#210000000
1!
1&
#211000000
0!
0&
#212000000
1!
1&
#213000000
0!
0&
#214000000
1!
1&
#215000000
0!
0&
#216000000
1!
1&
#217000000
0!
0&
#218000000
1!
1&
#219000000
0!
0&
#220000000
1!
1&
#221000000
0!
0&
#222000000
1!
1&
#223000000
0!
0&
#224000000
1!
1&
#225000000
0!
0&
#226000000
1!
1&
#227000000
0!
0&
#228000000
1!
1&
#229000000
0!
0&
#230000000
1!
1&
#231000000
0!
0&
#232000000
1!
1&
#233000000
0!
0&
#234000000
1!
1&
#235000000
0!
0&
#236000000
1!
1&
#237000000
0!
0&
#238000000
1!
1&
#239000000
0!
0&
#240000000
1!
1&
#241000000
0!
0&
#242000000
1!
1&
#243000000
0!
0&
#244000000
1!
1&
#245000000
0!
0&
#246000000
1!
1&
#247000000
0!
0&
#248000000
1!
1&
#249000000
0!
0&
#250000000
1!
1&
#251000000
0!
0&
#252000000
1!
1&
#253000000
0!
0&
#254000000
1!
1&
#255000000
0!
0&
#256000000
1!
1&
#257000000
0!
0&
#258000000
1!
1&
#259000000
0!
0&
#260000000
1!
1&
#261000000
0!
0&
#262000000
1!
1&
#263000000
0!
0&
#264000000
1!
1&
#265000000
0!
0&
#266000000
1!
1&
#267000000
0!
0&
#268000000
1!
1&
#269000000
0!
0&
#270000000
1!
1&
#271000000
0!
0&
#272000000
1!
1&
#273000000
0!
0&
#274000000
1!
1&
#275000000
0!
0&
#276000000
1!
1&
#277000000
0!
0&
#278000000
1!
1&
#279000000
0!
0&
#280000000
1!
1&
#281000000
0!
0&
#282000000
1!
1&
#283000000
0!
0&
#284000000
1!
1&
#285000000
0!
0&
#286000000
1!
1&
#287000000
0!
0&
#288000000
1!
1&
#289000000
0!
0&
#290000000
1!
1&
#291000000
0!
0&
#292000000
1!
1&
#293000000
0!
0&
#294000000
1!
1&
#295000000
0!
0&
#296000000
1!
1&
#297000000
0!
0&
#298000000
1!
1&
#299000000
0!
0&
#300000000
1!
1&
#301000000
0!
0&
#302000000
1!
1&
#303000000
0!
0&
#304000000
1!
1&
#305000000
0!
0&
#306000000
1!
1&
#307000000
0!
0&
#308000000
1!
1&
#309000000
0!
0&
#310000000
1!
1&
#311000000
0!
0&
#312000000
1!
1&
#313000000
0!
0&
#314000000
1!
1&
#315000000
0!
0&
#316000000
1!
1&
#317000000
0!
0&
#318000000
1!
1&
#319000000
0!
0&
#320000000
1!
1&
#321000000
0!
0&
#322000000
1!
1&
#323000000
0!
0&
#324000000
1!
1&
#325000000
0!
0&
#326000000
1!
1&
#327000000
0!
0&
#328000000
1!
1&
#329000000
0!
0&
#330000000
1!
1&
#331000000
0!
0&
#332000000
1!
1&
#333000000
0!
0&
#334000000
1!
1&
#335000000
0!
0&
#336000000
1!
1&
#337000000
0!
0&
#338000000
1!
1&
#339000000
0!
0&
#340000000
1!
1&
#341000000
0!
0&
#342000000
1!
1&
#343000000
0!
0&
#344000000
1!
1&
#345000000
0!
0&
#346000000
1!
1&
#347000000
0!
0&
#348000000
1!
1&
#349000000
0!
0&
#350000000
1!
1&
#351000000
0!
0&
#352000000
1!
1&
#353000000
0!
0&
#354000000
1!
1&
#355000000
0!
0&
#356000000
1!
1&
#357000000
0!
0&
#358000000
1!
1&
#359000000
0!
0&
#360000000
1!
1&
#361000000
0!
0&
#362000000
1!
1&
#363000000
0!
0&
#364000000
1!
1&
#365000000
0!
0&
#366000000
1!
1&
#367000000
0!
0&
#368000000
1!
1&
#369000000
0!
0&
#370000000
1!
1&
#371000000
0!
0&
#372000000
1!
1&
#373000000
0!
0&
#374000000
1!
1&
#375000000
0!
0&
#376000000
1!
1&
#377000000
0!
0&
#378000000
1!
1&
#379000000
0!
0&
#380000000
1!
1&
#381000000
0!
0&
#382000000
1!
1&
#383000000
0!
0&
#384000000
1!
1&
#385000000
0!
0&
#386000000
1!
1&
#387000000
0!
0&
#388000000
1!
1&
#389000000
0!
0&
#390000000
1!
1&
#391000000
0!
0&
#392000000
1!
1&
#393000000
0!
0&
#394000000
1!
1&
#395000000
0!
0&
#396000000
1!
1&
#397000000
0!
0&
#398000000
1!
1&
#399000000
0!
0&
#400000000
1!
1&
#401000000
0!
0&
#402000000
1!
1&
#403000000
0!
0&
#404000000
1!
1"
1&
1'
1(
#405000000
0!
0&
#406000000
1!
1&
0(
#407000000
0!
0&
#408000000
1!
1&
#409000000
0!
0&
#410000000
1!
1&
#411000000
0!
0&
#412000000
1!
0"
1&
0'
