zad3/top.vhd
library ieee;
use ieee.std_logic_1164.all;
use ieee.numeric_std.all;


entity top is
    port (
        oneh : in unsigned(7 downto 0);
        onel : in unsigned(7 downto 0);
        onesubper : in unsigned(7 downto 0);
        zeroh : in unsigned(7 downto 0);
        zerol : in unsigned(7 downto 0);
        zerosubper : in unsigned(7 downto 0);
        mi : in std_logic;
        mc : out std_logic := '0';
        sigval : in std_logic_vector(7 downto 0);
        modsig : out std_logic:= '0';
        fclk: in std_logic
    );
end top;


architecture arctop of top is
begin 
    main:process(fclk)
    variable idx:integer := 7;
    variable cnt: unsigned(7 downto 0) := x"00";
    variable cntl: unsigned(7 downto 0) := x"00";
    variable cnth: unsigned(7 downto 0) := x"00";
    variable cntsubper:unsigned(7 downto 0) := x"00";
    variable period: unsigned (7 downto 0) := x"00";
    variable h_flag : std_logic := '0';
    variable l_flag : std_logic := '0';
    variable mc_temp: std_logic := '0';
    variable next_bit_flag: std_logic := '0';
    variable temp_mod_signal: std_logic := '0';
    

   
    begin
        if falling_edge(fclk) then
            if falling_edge(mi) then
                mc_temp := '1';
                next_bit_flag := '1';
                cnth := x"00";
                cntl := x"00";
                cnt := x"00";
                cntsubper := x"00";
                period := x"00";
                h_flag := '0';
                l_flag := '0';
                temp_mod_signal := '0';
            end if;

            if rising_edge(mi) then
                mc_temp := '0';
            end if;

            mc <= mc_temp; 
            
            if mi = '1' or mc_temp = '0' then 
                
                if sigval(idx) = '1' then 
                    
                    next_bit_flag := '0';
                    cnt := cnt + 1;
                    if cnt < (onel + oneh)  then    
                        if cntl < onel then
                            modsig <= '0';
                            cntl := cntl + 1;
                        else 
                            h_flag := '1';
                        end if; 
                        
                        if h_flag = '1' then
                            if cnth <  oneh then

                                if cntsubper = ((onesubper/2) * period) then
                                    modsig <= temp_mod_signal xor '1';
                                    temp_mod_signal:= temp_mod_signal xor '1';
                                    period := period + 1;
                                end if;
                                
                                cntsubper := cntsubper + 1;
                                cnth := cnth + 1;
                            end if;                
                        end if; 
                        
                    
                    else
                        next_bit_flag := '1';
                        cnth := x"00";
                        cntl := x"00";
                        cnt := x"00";
                        cntsubper := x"00";
                        period := x"00";
                        h_flag := '0';
                        l_flag := '0';
                        temp_mod_signal := '0';
                    end if; 
                    
                end if; 


                if sigval(idx) = '0' then 
                    next_bit_flag := '0';
                    cnt := cnt + 1;
                    if cnt < (zerol + zeroh) then    
                        if cnth < zeroh then
                            if cntsubper = ((zerosubper/2) * period) then
                                modsig <= not (temp_mod_signal xor '1');
                                temp_mod_signal:= temp_mod_signal xor '1';
                                period := period + 1;
                            end if;
                            
                            cntsubper := cntsubper + 1;
                            cnth := cnth + 1;
                            
                        else 
                            l_flag := '1';
                        end if; 
                        
                        if l_flag = '1' then
                            if cntl <  zerol then
                           
                                modsig <= '0';
                                cntl := cntl + 1;
                                
                            end if;                 

                        end if; 
                        
                    
                    else
                        next_bit_flag := '1';
                        cnth := x"00";
                        cntl := x"00";
                        cnt := x"00";
                        cntsubper := x"00";
                        period := x"00";
                        h_flag := '0';
                        l_flag := '0';
                        temp_mod_signal := '0';
                    end if; 
                    
                end if;                                 

                if next_bit_flag = '1' then
                    idx := idx - 1; 
                end if; 

                if idx < 0 then
                    mc_temp := '1';   
                end if;
                
            end if;   

            if mc_temp = '1' then
                idx := 7;
                modsig <= '0';
            end if;           
        end if;   
    end process;
end arctop;

zadaca1/zad3/top_tb.vhd
library ieee;
use ieee.std_logic_1164.all;
use ieee.numeric_std.all;

entity top_tb is
end top_tb;

architecture arctop_tb of top_tb is
component top 
    port(
    oneh : in unsigned(7 downto 0);
    onel : in unsigned(7 downto 0);
    onesubper : in unsigned(7 downto 0);
    zeroh : in unsigned(7 downto 0);
    zerol : in unsigned(7 downto 0);
    zerosubper : in unsigned(7 downto 0);
    mi : in std_logic;
    mc : out std_logic := '0';
    sigval : in std_logic_vector(7 downto 0);
    modsig : out std_logic:= '0';
    fclk: in std_logic
    );
end component;

signal oneh :  unsigned(7 downto 0) := x"00";
signal onel :  unsigned(7 downto 0) := x"00";
signal onesubper : unsigned(7 downto 0):= x"00";
signal zeroh : unsigned(7 downto 0):= x"00";
signal zerol : unsigned(7 downto 0):= x"00";
signal zerosubper :  unsigned(7 downto 0):= x"00";
signal mi : std_logic := '0';
signal mc : std_logic := '0';
signal sigval :  std_logic_vector(7 downto 0) := x"00";
signal modsig :  std_logic:= '0';
signal fclk: std_logic :='0';

begin 
    main: top port map(fclk => fclk, modsig => modsig, sigval => sigval, mc => mc, mi => mi, zerosubper => zerosubper, zerol => zerol, zeroh => zeroh, onesubper => onesubper, onel => onel, oneh => oneh);

    process
    begin
        assert false report "start simulation";
		fclk <= '0'; 
        oneh <= x"32";
        onel <= x"64";
        onesubper <= x"0A";
        zeroh <= x"1E";
        zerol <= x"5A";
        zerosubper <= x"0A";
        sigval <= x"DE"; 
        mi <= '1';
        for k in 0 to 1200 loop
            wait for 0.5 ns;
            fclk <= '1';
            wait for 0.5 ns;
            fclk <= '0';
        end loop;
        mi<='0';
        for k in 0 to 50 loop
            wait for 0.5 ns;
            fclk <= '1';
            wait for 0.5 ns;
            fclk <= '0';
        end loop;
        sigval <= x"AD";
        mi<='1';
        for k in 0 to 1200 loop
            wait for 0.5 ns;
            fclk <= '1';
            wait for 0.5 ns;
            fclk <= '0';
        end loop;
        mi<='0';

        for k in 0 to 50 loop
            wait for 0.5 ns;
            fclk <= '1';
            wait for 0.5 ns;
            fclk <= '0';
        end loop;
        sigval <= x"BE";
        mi<='1';
        for k in 0 to 1200 loop
            wait for 0.5 ns;
            fclk <= '1';
            wait for 0.5 ns;
            fclk <= '0';
        end loop;
        mi<='0';

        for k in 0 to 50 loop
            wait for 0.5 ns;
            fclk <= '1';
            wait for 0.5 ns;
            fclk <= '0';
        end loop;
        sigval <= x"EF";
        mi<='1';
        for k in 0 to 1200 loop
            wait for 0.5 ns;
            fclk <= '1';
            wait for 0.5 ns;
            fclk <= '0';
        end loop;
        mi<='0';
        assert false report "test completed";
		wait;
		
	end process;
end arctop_tb;

zadaca1/zad3/top.vcd
$date
  Wed May  8 17:00:41 2024
$end
$version
  GHDL v0
$end
$timescale
  1 fs
$end
$scope module standard $end
$upscope $end
$scope module std_logic_1164 $end
$upscope $end
$scope module numeric_std $end
$upscope $end
$scope module top_tb $end
$var reg 8 ! oneh[7:0] $end
$var reg 8 " onel[7:0] $end
$var reg 8 # onesubper[7:0] $end
$var reg 8 $ zeroh[7:0] $end
$var reg 8 % zerol[7:0] $end
$var reg 8 & zerosubper[7:0] $end
$var reg 1 ' mi $end
$var reg 1 ( mc $end
$var reg 8 ) sigval[7:0] $end
$var reg 1 * modsig $end
$var reg 1 + fclk $end
$scope module main $end
$var reg 8 , oneh[7:0] $end
$var reg 8 - onel[7:0] $end
$var reg 8 . onesubper[7:0] $end
$var reg 8 / zeroh[7:0] $end
$var reg 8 0 zerol[7:0] $end
$var reg 8 1 zerosubper[7:0] $end
$var reg 1 2 mi $end
$var reg 1 3 mc $end
$var reg 8 4 sigval[7:0] $end
$var reg 1 5 modsig $end
$var reg 1 6 fclk $end
$upscope $end
$upscope $end
$enddefinitions $end
#0
b00110010 !
b01100100 "
b00001010 #
b00011110 $
b01011010 %
b00001010 &
1'
0(
b11011110 )
0*
0+
b00110010 ,
b01100100 -
b00001010 .
b00011110 /
b01011010 0
b00001010 1
12
03
b11011110 4
05
06
#500000
1+
16
#1000000
0+
06
#1500000
1+
16
#2000000
0+
06
#2500000
1+
16
#3000000
0+
06
#3500000
1+
16
#4000000
0+
06
#4500000
1+
16
#5000000
0+
06
#5500000
1+
16
#6000000
0+
06
#6500000
1+
16
#7000000
0+
06
#7500000
1+
16
#8000000
0+
06
#8500000
1+
16
#9000000
0+
06
#9500000
1+
16
#10000000
0+
06
#10500000
1+
16
#11000000
0+
06
#11500000
1+
16
#12000000
0+
06
#12500000
1+
16
#13000000
0+
06
#13500000
1+
16
#14000000
0+
06
#14500000
1+
16
#15000000
0+
06
#15500000
1+
16
#16000000
0+
06
#16500000
1+
16
#17000000
0+
06
#17500000
1+
16
#18000000
0+
06
#18500000
1+
16
#19000000
0+
06
#19500000
1+
16
#20000000
0+
06
#20500000
1+
16
#21000000
0+
06
#21500000
1+
16
#22000000
0+
06
#22500000
1+
16
#23000000
0+
06
#23500000
1+
16
#24000000
0+
06
#24500000
1+
16
#25000000
0+
06
#25500000
1+
16
#26000000
0+
06
#26500000
1+
16
#27000000
0+
06
#27500000
1+
16
#28000000
0+
06
#28500000
1+
16
#29000000
0+
06
#29500000
1+
16
#30000000
0+
06
#30500000
1+
16
#31000000
0+
06
#31500000
1+
16
#32000000
0+
06
#32500000
1+
16
#33000000
0+
06
#33500000
1+
16
#34000000
0+
06
#34500000
1+
16
#35000000
0+
06
#35500000
1+
16
#36000000
0+
06
#36500000
1+
16
#37000000
0+
06
#37500000
1+
16
#38000000
0+
06
#38500000
1+
16
#39000000
0+
06
#39500000
1+
16
#40000000
0+
06
#40500000
1+
16
#41000000
0+
06
#41500000
1+
16
#42000000
0+
06
#42500000
1+
16
#43000000
0+
06
#43500000
1+
16
#44000000
0+
06
#44500000
1+
16
#45000000
0+
06
#45500000
1+
16
#46000000
0+
06
#46500000
1+
16
#47000000
0+
06
#47500000
1+
16
#48000000
0+
06
#48500000
1+
16
#49000000
0+
06
#49500000
1+
16
#50000000
0+
06
#50500000
1+
16
#51000000
0+
06
#51500000
1+
16
#52000000
0+
06
#52500000
1+
16
#53000000
0+
06
#53500000
1+
16
#54000000
0+
06
#54500000
1+
16
#55000000
0+
06
#55500000
1+
16
#56000000
0+
06
#56500000
1+
16
#57000000
0+
06
#57500000
1+
16
#58000000
0+
06
#58500000
1+
16
#59000000
0+
06
#59500000
1+
16
#60000000
0+
06
#60500000
1+
16
#61000000
0+
06
#61500000
1+
16
#62000000
0+
06
#62500000
1+
16
#63000000
0+
06
#63500000
1+
16
#64000000
0+
06
#64500000
1+
16
#65000000
0+
06
#65500000
1+
16
#66000000
0+
06
#66500000
1+
16
#67000000
0+
06
#67500000
1+
16
#68000000
0+
06
#68500000
1+
16
#69000000
0+
06
#69500000
1+
16
#70000000
0+
06
#70500000
1+
16
#71000000
0+
06
#71500000
1+
16
#72000000
0+
06
#72500000
1+
16
#73000000
0+
06
#73500000
1+
16
#74000000
0+
06
#74500000
1+
16
#75000000
0+
06
#75500000
1+
16
#76000000
0+
06
#76500000
1+
16
#77000000
0+
06
#77500000
1+
16
#78000000
0+
06
#78500000
1+
16
#79000000
0+
06
#79500000
1+
16
#80000000
0+
06
#80500000
1+
16
#81000000
0+
06
#81500000
1+
16
#82000000
0+
06
#82500000
1+
16
#83000000
0+
06
#83500000
1+
16
#84000000
0+
06
#84500000
1+
16
#85000000
0+
06
#85500000
1+
16
#86000000
0+
06
#86500000
1+
16
#87000000
0+
06
#87500000
1+
16
#88000000
0+
06
#88500000
1+
16
#89000000
0+
06
#89500000
1+
16
#90000000
0+
06
#90500000
1+
16
#91000000
0+
06
#91500000
1+
16
#92000000
0+
06
#92500000
1+
16
#93000000
0+
06
#93500000
1+
16
#94000000
0+
06
#94500000
1+
16
#95000000
0+
06
#95500000
1+
16
#96000000
0+
06
#96500000
1+
16
#97000000
0+
06
#97500000
1+
16
#98000000
0+
06
#98500000
1+
16
#99000000
0+
06
#99500000
1+
16
#100000000
0+
06
#100500000
1+
16
#101000000
1*
0+
15
06
#101500000
1+
16
#102000000
0+
06
#102500000
1+
16
#103000000
0+
06
#103500000
1+
16
#104000000
0+
06
#104500000
1+
16
#105000000
0+
06
#105500000
1+
16
#106000000
0*
0+
05
06
#106500000
1+
16
#107000000
0+
06
#107500000
1+
16
#108000000
0+
06
#108500000
1+
16
#109000000
0+
06
#109500000
1+
16
#110000000
0+
06
#110500000
1+
16
#111000000
1*
0+
15
06
#111500000
1+
16
#112000000
0+
06
#112500000
1+
16
#113000000
0+
06
#113500000
1+
16
#114000000
0+
06
#114500000
1+
16
#115000000
0+
06
#115500000
1+
16
#116000000
0*
0+
05
06
#116500000
1+
16
#117000000
0+
06
#117500000
1+
16
#118000000
0+
06
#118500000
1+
16
#119000000
0+
06
#119500000
1+
16
#120000000
0+
06
#120500000
1+
16
#121000000
1*
0+
15
06
#121500000
1+
16
#122000000
0+
06
#122500000
1+
16
#123000000
0+
06
#123500000
1+
16
#124000000
0+
06
#124500000
1+
16
#125000000
0+
06
#125500000
1+
16
#126000000
0*
0+
05
06
#126500000
1+
16
#127000000
0+
06
#127500000
1+
16
#128000000
0+
06
#128500000
1+
16
#129000000
0+
06
#129500000
1+
16
#130000000
0+
06
#130500000
1+
16
#131000000
1*
0+
15
06
#131500000
1+
16
#132000000
0+
06
#132500000
1+
16
#133000000
0+
06
#133500000
1+
16
#134000000
0+
06
#134500000
1+
16
#135000000
0+
06
#135500000
1+
16
#136000000
0*
0+
05
06
#136500000
1+
16
#137000000
0+
06
#137500000
1+
16
#138000000
0+
06
#138500000
1+
16
#139000000
0+
06
#139500000
1+
16
#140000000
0+
06
#140500000
1+
16
#141000000
1*
0+
15
06
#141500000
1+
16
#142000000
0+
06
#142500000
1+
16
#143000000
0+
06
#143500000
1+
16
#144000000
0+
06
#144500000
1+
16
#145000000
0+
06
#145500000
1+
16
#146000000
0*
0+
05
06
